pyweblight/__init__.py
pyweblight/configs.py
pyweblight/main.py
pyweblight/static.py
pyweblight/webserver_start.py
pyweblight/webserver_stop.py
pyweblight-0.0.6.dist-info/LICENSE
pyweblight-0.0.6.dist-info/METADATA
pyweblight-0.0.6.dist-info/WHEEL
pyweblight-0.0.6.dist-info/entry_points.txt
pyweblight-0.0.6.dist-info/top_level.txt
pyweblight-0.0.6.dist-info/RECORD
