Metadata-Version: 2.1
Name: pyweblight
Version: 0.0.6
Summary: Pyweblight is a small configurable web server for developers
Home-page: https://veltzer.github.io/pyweblight
Download-URL: https://github.com/veltzer/pyweblight
Author: Mark Veltzer
Author-email: mark.veltzer@gmail.com
Maintainer: Mark Veltzer
Maintainer-email: mark.veltzer@gmail.com
License: MIT
Keywords: http,https,apache,python,python3,server,web
Platform: python3
Classifier: Development Status :: 4 - Beta
Classifier: Environment :: Console
Classifier: Operating System :: OS Independent
Classifier: Programming Language :: Python
Classifier: Programming Language :: Python :: 3
Classifier: Programming Language :: Python :: 3 :: Only
Classifier: Programming Language :: Python :: 3.11
Classifier: Topic :: Utilities
Classifier: License :: OSI Approved :: MIT License
License-File: LICENSE
Requires-Dist: python-daemon
Requires-Dist: pytconf
Requires-Dist: pylogconf
